pytimeparser/__init__.py
pytimeparser/api.py
pytimeparser/utils.py
pytimeparser-0.2.0.dist-info/DESCRIPTION.rst
pytimeparser-0.2.0.dist-info/METADATA
pytimeparser-0.2.0.dist-info/RECORD
pytimeparser-0.2.0.dist-info/WHEEL
pytimeparser-0.2.0.dist-info/metadata.json
pytimeparser-0.2.0.dist-info/top_level.txt
