Metadata-Version: 1.1
Name: pytimeparser
Version: 0.2.0
Summary: Basic Python module to parse time expressions.
Home-page: https://github.com/ouahibelhanchi/pytimeparser
Author: Ouahib El Hanchi
Author-email: ouahib.el.hanchi@gmail.com
License: MIT license
Keywords: pytimeparser
Platform: UNKNOWN
Classifier: Development Status :: 2 - Pre-Alpha
Classifier: Intended Audience :: Developers
Classifier: License :: OSI Approved :: MIT License
Classifier: Natural Language :: English
Classifier: Programming Language :: Python :: 2
Classifier: Programming Language :: Python :: 2.7
Classifier: Programming Language :: Python :: 3
Classifier: Programming Language :: Python :: 3.4
Classifier: Programming Language :: Python :: 3.5
Classifier: Programming Language :: Python :: 3.6
